Workbook

Sheet LÉEME
A1: Sistema Comercial Marli — Plantilla Excel
A3: Esta plantilla recoge todo el sistema de gestión comercial: equipo, productos, pipeline de leads, comisiones y ranking. Está pensada para trabajar en local sin depender de servicios externos.
A5: Orden de hojas
A6: Equipo | B6: Una fila por persona. El rol y la pareja determinan a quién va cada lead y qué comisión cobra.
A7: Productos | B7: Catálogo con precio, coste y margen. Todas las comisiones se calculan sobre el MARGEN.
A8: Parejas | B8: Mapeo Pareja→Setter→Closer→% comisiones. Solo se toca si cambias parejas o porcentajes.
A9: Leads | B9: Pipeline. Aquí trabaja el equipo. Las columnas grises se calculan solas.
A10: Ranking | B10: Métricas por setter y lote: tasa de contacto, agendado, presentación, cierre, € facturados, € comisión.
A11: Comisiones | B11: Resumen mensual por persona. Se rellena solo a partir de Leads.
A12: Round-Robin | B12: Generador del campo 'Pareja asignada' para los 10.000 leads fríos.
A14: Reglas de oro
A15: 1. Una venta solo genera comisión si Estado='cerrado' y la Ficha estaba completa antes de la videollamada.
A16: 2. Comisiones siempre sobre MARGEN, nunca sobre precio.
A17: 3. Mantenimiento contratado = 50 € únicos extra al closer.
A18: 4. No tocar columnas grises (fórmulas). Solo se introduce dato en las blancas.
A19: 5. Los desplegables están protegidos: usa solo los valores válidos.
A22: Productos y márgenes (referencia rápida)
A23: Producto | B23: Precio | C23: Coste agencia | D23: Margen | E23: Setter (5%) | F23: Closer (15%)
A24: Automatización Informes | B24: 449 | C24: 200 | D24: 249 | E24: 12.45 | F24: 37.35
A25: Chatbot IA | B25: 999 | C25: 500 | D25: 499 | E25: 24.95 | F25: 74.85
A26: Pack Premium | B26: 1349 | C26: 700 | D26: 649 | E26: 32.45 | F26: 97.35
A27: Mantenimiento (300€/mes) | B27: - | C27: - | D27: - | E27: - | F27: +50€ únicos al closer

Sheet Equipo
A1: ID | B1: Nombre | C1: Rol | D1: Email | E1: Pareja | F1: Comisión % | G1: Activo
A2: E01 | B2: Lucía | C2: setter | D2: lucia@marliagency.com | E2: Lucia-Diego | F2: 0.05 | G2: TRUE
A3: E02 | B3: Marta | C3: setter | D3: marta@marliagency.com | E3: Marta-Sara | F3: 0.05 | G3: TRUE
A4: E03 | B4: Diego | C4: closer | D4: diego@marliagency.com | E4: Lucia-Diego | F4: 0.15 | G4: TRUE
A5: E04 | B5: Sara | C5: closer | D5: sara@marliagency.com | E5: Marta-Sara | F5: 0.15 | G5: TRUE
A6: E05 | B6: José | C6: closer | D6: jose@marliagency.com | E6: Jose | F6: 0.2 | G6: TRUE

Sheet Productos
A1: ID | B1: Nombre | C1: Precio | D1: Coste agencia | E1: Margen | F1: Tipo | G1: Notas
A2: P01 | B2: Automatización Informes | C2: 449 | D2: 200 | E2: =C2-D2 | F2: one-time | G2: Informes automatizados para psicólogos
A3: P02 | B3: Chatbot IA | C3: 999 | D3: 500 | E3: =C3-D3 | F3: one-time | G3: Chatbot conversacional con IA
A4: P03 | B4: Pack Premium | C4: 1349 | D4: 700 | E4: =C4-D4 | F4: one-time | G4: Informes + Chatbot integrados
A5: P04 | B5: Mantenimiento | C5: 300 | D5: 0 | E5: =C5-D5 | F5: monthly | G5: Suscripción mensual. 50€ únicos al closer cuando se contrata.

Sheet Parejas
A1: Pareja | B1: Setter | C1: Closer | D1: Setter % | E1: Closer % | F1: Notas
A2: Lucia-Diego | B2: Lucía | C2: Diego | D2: 0.05 | E2: 0.15 | F2: Pareja estándar
A3: Marta-Sara | B3: Marta | C3: Sara | D3: 0.05 | E3: 0.15 | F3: Pareja estándar
A4: Jose | B4: José | C4: José | D4: 0.2 | E4: 0.2 | F4: José vende en solitario (closer 20%)
A5: Jose-asistido | B5: Otro setter | C5: José | D5: 0.05 | E5: 0.1 | F5: Setter agenda, José cierra (10% closer)

Sheet Leads
A1: ID lead | B1: Nombre psicólogo | C1: Email | D1: Teléfono | E1: Ciudad | F1: Lote | G1: Pareja asignada | H1: Setter | I1: Closer derivado | J1: Estado | K1: Fecha último cambio | L1: Dolor detectado | M1: Nº pacientes | N1: Objeción anticipada | O1: Fecha videollamada | P1: Ficha completa | Q1: Producto | R1: Precio | S1: Margen | T1: Euros cobrado | U1: Mantenimiento | V1: Comisión setter | W1: Comisión closer | X1: Bonus mantenimiento | Y1: Notas
A2: L0001 | B2: Clínica Ana Rodríguez | C2: ana@clinica.com | D2: 611111111 | E2: Madrid | F2: 1 | G2: Lucia-Diego | H2: =IFERROR(VLOOKUP(G2,Parejas!A:F,2,FALSE),"") | I2: =IFERROR(VLOOKUP(G2,Parejas!A:F,3,FALSE),"") | J2: presentado | K2: 2026-05-20 | L2: No capta pacientes online | M2: 35 | N2: Precio alto | O2: 2026-05-22 | P2: =IF(AND(L2<>"",M2<>"",N2<>"",O2<>""),"✅","❌") | Q2: Pack Premium | R2: =IFERROR(VLOOKUP(Q2,Productos!B:F,2,FALSE),"") | S2: =IFERROR(VLOOKUP(Q2,Productos!B:F,4,FALSE),"") | T2: 0 | U2: FALSE | V2: =IFERROR(IF(J2="cerrado",S2*VLOOKUP(G2,Parejas!A:E,4,FALSE),0),0) | W2: =IFERROR(IF(J2="cerrado",S2*VLOOKUP(G2,Parejas!A:E,5,FALSE),0),0) | X2: =IF(AND(J2="cerrado",U2=TRUE),50,0)
A3: L0002 | B3: Centro Psicología Luna | C3: info@luna.es | D3: 622222222 | E3: Barcelona | F3: 1 | G3: Marta-Sara | H3: =IFERROR(VLOOKUP(G3,Parejas!A:F,2,FALSE),"") | I3: =IFERROR(VLOOKUP(G3,Parejas!A:F,3,FALSE),"") | J3: cerrado | K3: 2026-05-25 | L3: Quiere captar más jóvenes | M3: 60 | N3: Tiempo de implantación | O3: 2026-05-24 | P3: =IF(AND(L3<>"",M3<>"",N3<>"",O3<>""),"✅","❌") | Q3: Chatbot IA | R3: =IFERROR(VLOOKUP(Q3,Productos!B:F,2,FALSE),"") | S3: =IFERROR(VLOOKUP(Q3,Productos!B:F,4,FALSE),"") | T3: 999 | U3: TRUE | V3: =IFERROR(IF(J3="cerrado",S3*VLOOKUP(G3,Parejas!A:E,4,FALSE),0),0) | W3: =IFERROR(IF(J3="cerrado",S3*VLOOKUP(G3,Parejas!A:E,5,FALSE),0),0) | X3: =IF(AND(J3="cerrado",U3=TRUE),50,0) | Y3: Cerrado + mantenimiento
A4: L0003 | B4: Psicólogo Juan Pérez | C4: juan@gabinete.com | D4: 633333333 | E4: Valencia | F4: 1 | G4: Jose | H4: =IFERROR(VLOOKUP(G4,Parejas!A:F,2,FALSE),"") | I4: =IFERROR(VLOOKUP(G4,Parejas!A:F,3,FALSE),"") | J4: contactado | K4: 2026-05-26 | L4: Solo, sin equipo | M4: 12 | N4: Duda si IA cuadra con su perfil | P4: =IF(AND(L4<>"",M4<>"",N4<>"",O4<>""),"✅","❌") | R4: =IFERROR(VLOOKUP(Q4,Productos!B:F,2,FALSE),"") | S4: =IFERROR(VLOOKUP(Q4,Productos!B:F,4,FALSE),"") | T4: 0 | U4: FALSE | V4: =IFERROR(IF(J4="cerrado",S4*VLOOKUP(G4,Parejas!A:E,4,FALSE),0),0) | W4: =IFERROR(IF(J4="cerrado",S4*VLOOKUP(G4,Parejas!A:E,5,FALSE),0),0) | X4: =IF(AND(J4="cerrado",U4=TRUE),50,0)
H5: =IFERROR(VLOOKUP(G5,Parejas!A:F,2,FALSE),"") | I5: =IFERROR(VLOOKUP(G5,Parejas!A:F,3,FALSE),"") | P5: =IF(AND(L5<>"",M5<>"",N5<>"",O5<>""),"✅","❌") | R5: =IFERROR(VLOOKUP(Q5,Productos!B:F,2,FALSE),"") | S5: =IFERROR(VLOOKUP(Q5,Productos!B:F,4,FALSE),"") | V5: =IFERROR(IF(J5="cerrado",S5*VLOOKUP(G5,Parejas!A:E,4,FALSE),0),0) | W5: =IFERROR(IF(J5="cerrado",S5*VLOOKUP(G5,Parejas!A:E,5,FALSE),0),0) | X5: =IF(AND(J5="cerrado",U5=TRUE),50,0)
H6: =IFERROR(VLOOKUP(G6,Parejas!A:F,2,FALSE),"") | I6: =IFERROR(VLOOKUP(G6,Parejas!A:F,3,FALSE),"") | P6: =IF(AND(L6<>"",M6<>"",N6<>"",O6<>""),"✅","❌") | R6: =IFERROR(VLOOKUP(Q6,Productos!B:F,2,FALSE),"") | S6: =IFERROR(VLOOKUP(Q6,Productos!B:F,4,FALSE),"") | V6: =IFERROR(IF(J6="cerrado",S6*VLOOKUP(G6,Parejas!A:E,4,FALSE),0),0) | W6: =IFERROR(IF(J6="cerrado",S6*VLOOKUP(G6,Parejas!A:E,5,FALSE),0),0) | X6: =IF(AND(J6="cerrado",U6=TRUE),50,0)
H7: =IFERROR(VLOOKUP(G7,Parejas!A:F,2,FALSE),"") | I7: =IFERROR(VLOOKUP(G7,Parejas!A:F,3,FALSE),"") | P7: =IF(AND(L7<>"",M7<>"",N7<>"",O7<>""),"✅","❌") | R7: =IFERROR(VLOOKUP(Q7,Productos!B:F,2,FALSE),"") | S7: =IFERROR(VLOOKUP(Q7,Productos!B:F,4,FALSE),"") | V7: =IFERROR(IF(J7="cerrado",S7*VLOOKUP(G7,Parejas!A:E,4,FALSE),0),0) | W7: =IFERROR(IF(J7="cerrado",S7*VLOOKUP(G7,Parejas!A:E,5,FALSE),0),0) | X7: =IF(AND(J7="cerrado",U7=TRUE),50,0)
H8: =IFERROR(VLOOKUP(G8,Parejas!A:F,2,FALSE),"") | I8: =IFERROR(VLOOKUP(G8,Parejas!A:F,3,FALSE),"") | P8: =IF(AND(L8<>"",M8<>"",N8<>"",O8<>""),"✅","❌") | R8: =IFERROR(VLOOKUP(Q8,Productos!B:F,2,FALSE),"") | S8: =IFERROR(VLOOKUP(Q8,Productos!B:F,4,FALSE),"") | V8: =IFERROR(IF(J8="cerrado",S8*VLOOKUP(G8,Parejas!A:E,4,FALSE),0),0) | W8: =IFERROR(IF(J8="cerrado",S8*VLOOKUP(G8,Parejas!A:E,5,FALSE),0),0) | X8: =IF(AND(J8="cerrado",U8=TRUE),50,0)
H9: =IFERROR(VLOOKUP(G9,Parejas!A:F,2,FALSE),"") | I9: =IFERROR(VLOOKUP(G9,Parejas!A:F,3,FALSE),"") | P9: =IF(AND(L9<>"",M9<>"",N9<>"",O9<>""),"✅","❌") | R9: =IFERROR(VLOOKUP(Q9,Productos!B:F,2,FALSE),"") | S9: =IFERROR(VLOOKUP(Q9,Productos!B:F,4,FALSE),"") | V9: =IFERROR(IF(J9="cerrado",S9*VLOOKUP(G9,Parejas!A:E,4,FALSE),0),0) | W9: =IFERROR(IF(J9="cerrado",S9*VLOOKUP(G9,Parejas!A:E,5,FALSE),0),0) | X9: =IF(AND(J9="cerrado",U9=TRUE),50,0)
H10: =IFERROR(VLOOKUP(G10,Parejas!A:F,2,FALSE),"") | I10: =IFERROR(VLOOKUP(G10,Parejas!A:F,3,FALSE),"") | P10: =IF(AND(L10<>"",M10<>"",N10<>"",O10<>""),"✅","❌") | R10: =IFERROR(VLOOKUP(Q10,Productos!B:F,2,FALSE),"") | S10: =IFERROR(VLOOKUP(Q10,Productos!B:F,4,FALSE),"") | V10: =IFERROR(IF(J10="cerrado",S10*VLOOKUP(G10,Parejas!A:E,4,FALSE),0),0) | W10: =IFERROR(IF(J10="cerrado",S10*VLOOKUP(G10,Parejas!A:E,5,FALSE),0),0) | X10: =IF(AND(J10="cerrado",U10=TRUE),50,0)
H11: =IFERROR(VLOOKUP(G11,Parejas!A:F,2,FALSE),"") | I11: =IFERROR(VLOOKUP(G11,Parejas!A:F,3,FALSE),"") | P11: =IF(AND(L11<>"",M11<>"",N11<>"",O11<>""),"✅","❌") | R11: =IFERROR(VLOOKUP(Q11,Productos!B:F,2,FALSE),"") | S11: =IFERROR(VLOOKUP(Q11,Productos!B:F,4,FALSE),"") | V11: =IFERROR(IF(J11="cerrado",S11*VLOOKUP(G11,Parejas!A:E,4,FALSE),0),0) | W11: =IFERROR(IF(J11="cerrado",S11*VLOOKUP(G11,Parejas!A:E,5,FALSE),0),0) | X11: =IF(AND(J11="cerrado",U11=TRUE),50,0)
H12: =IFERROR(VLOOKUP(G12,Parejas!A:F,2,FALSE),"") | I12: =IFERROR(VLOOKUP(G12,Parejas!A:F,3,FALSE),"") | P12: =IF(AND(L12<>"",M12<>"",N12<>"",O12<>""),"✅","❌") | R12: =IFERROR(VLOOKUP(Q12,Productos!B:F,2,FALSE),"") | S12: =IFERROR(VLOOKUP(Q12,Productos!B:F,4,FALSE),"") | V12: =IFERROR(IF(J12="cerrado",S12*VLOOKUP(G12,Parejas!A:E,4,FALSE),0),0) | W12: =IFERROR(IF(J12="cerrado",S12*VLOOKUP(G12,Parejas!A:E,5,FALSE),0),0) | X12: =IF(AND(J12="cerrado",U12=TRUE),50,0)
H13: =IFERROR(VLOOKUP(G13,Parejas!A:F,2,FALSE),"") | I13: =IFERROR(VLOOKUP(G13,Parejas!A:F,3,FALSE),"") | P13: =IF(AND(L13<>"",M13<>"",N13<>"",O13<>""),"✅","❌") | R13: =IFERROR(VLOOKUP(Q13,Productos!B:F,2,FALSE),"") | S13: =IFERROR(VLOOKUP(Q13,Productos!B:F,4,FALSE),"") | V13: =IFERROR(IF(J13="cerrado",S13*VLOOKUP(G13,Parejas!A:E,4,FALSE),0),0) | W13: =IFERROR(IF(J13="cerrado",S13*VLOOKUP(G13,Parejas!A:E,5,FALSE),0),0) | X13: =IF(AND(J13="cerrado",U13=TRUE),50,0)
H14: =IFERROR(VLOOKUP(G14,Parejas!A:F,2,FALSE),"") | I14: =IFERROR(VLOOKUP(G14,Parejas!A:F,3,FALSE),"") | P14: =IF(AND(L14<>"",M14<>"",N14<>"",O14<>""),"✅","❌") | R14: =IFERROR(VLOOKUP(Q14,Productos!B:F,2,FALSE),"") | S14: =IFERROR(VLOOKUP(Q14,Productos!B:F,4,FALSE),"") | V14: =IFERROR(IF(J14="cerrado",S14*VLOOKUP(G14,Parejas!A:E,4,FALSE),0),0) | W14: =IFERROR(IF(J14="cerrado",S14*VLOOKUP(G14,Parejas!A:E,5,FALSE),0),0) | X14: =IF(AND(J14="cerrado",U14=TRUE),50,0)
H15: =IFERROR(VLOOKUP(G15,Parejas!A:F,2,FALSE),"") | I15: =IFERROR(VLOOKUP(G15,Parejas!A:F,3,FALSE),"") | P15: =IF(AND(L15<>"",M15<>"",N15<>"",O15<>""),"✅","❌") | R15: =IFERROR(VLOOKUP(Q15,Productos!B:F,2,FALSE),"") | S15: =IFERROR(VLOOKUP(Q15,Productos!B:F,4,FALSE),"") | V15: =IFERROR(IF(J15="cerrado",S15*VLOOKUP(G15,Parejas!A:E,4,FALSE),0),0) | W15: =IFERROR(IF(J15="cerrado",S15*VLOOKUP(G15,Parejas!A:E,5,FALSE),0),0) | X15: =IF(AND(J15="cerrado",U15=TRUE),50,0)
H16: =IFERROR(VLOOKUP(G16,Parejas!A:F,2,FALSE),"") | I16: =IFERROR(VLOOKUP(G16,Parejas!A:F,3,FALSE),"") | P16: =IF(AND(L16<>"",M16<>"",N16<>"",O16<>""),"✅","❌") | R16: =IFERROR(VLOOKUP(Q16,Productos!B:F,2,FALSE),"") | S16: =IFERROR(VLOOKUP(Q16,Productos!B:F,4,FALSE),"") | V16: =IFERROR(IF(J16="cerrado",S16*VLOOKUP(G16,Parejas!A:E,4,FALSE),0),0) | W16: =IFERROR(IF(J16="cerrado",S16*VLOOKUP(G16,Parejas!A:E,5,FALSE),0),0) | X16: =IF(AND(J16="cerrado",U16=TRUE),50,0)
... H51: =IFERROR(VLOOKUP(G51,Parejas!A:F,2,FALSE),"") | I51: =IFERROR(VLOOKUP(G51,Parejas!A:F,3,FALSE),"") | P51: =IF(AND(L51<>"",M51<>"",N51<>"",O51<>""),"✅","❌") | R51: =IFERROR(VLOOKUP(Q51,Productos!B:F,2,FALSE),"") | S51: =IFERROR(VLOOKUP(Q51,Productos!B:F,4,FALSE),"") | V51: =IFERROR(IF(J51="cerrado",S51*VLOOKUP(G51,Parejas!A:E,4,FALSE),0),0) | W51: =IFERROR(IF(J51="cerrado",S51*VLOOKUP(G51,Parejas!A:E,5,FALSE),0),0) | X51: =IF(AND(J51="cerrado",U51=TRUE),50,0)

Sheet Ranking
A1: Ranking semanal por setter y lote
A2: Cambia el lote en B4 para filtrar. Las métricas se recalculan solas.
A4: Lote a analizar: | B4: 1
A6: Setter | B6: Total leads | C6: Contactados | D6: Agendados | E6: Presentados | F6: Cerrados | G6: Perdidos | H6: Tasa contacto | I6: Tasa agendado | J6: Tasa presentación | K6: Tasa cierre | L6: € facturado | M6: € comisión
A7: Lucía | B7: =COUNTIFS(Leads!H:H,A7,Leads!F:F,$B$4) | C7: =COUNTIFS(Leads!H:H,A7,Leads!F:F,$B$4,Leads!J:J,"<>frio") | D7: =COUNTIFS(Leads!H:H,A7,Leads!F:F,$B$4,Leads!J:J,"cita agendada")+COUNTIFS(Leads!H:H,A7,Leads!F:F,$B$4,Leads!J:J,"presentado")+COUNTIFS(Leads!H:H,A7,Leads!F:F,$B$4,Leads!J:J,"cerrado") | E7: =COUNTIFS(Leads!H:H,A7,Leads!F:F,$B$4,Leads!J:J,"presentado")+COUNTIFS(Leads!H:H,A7,Leads!F:F,$B$4,Leads!J:J,"cerrado") | F7: =COUNTIFS(Leads!H:H,A7,Leads!F:F,$B$4,Leads!J:J,"cerrado") | G7: =COUNTIFS(Leads!H:H,A7,Leads!F:F,$B$4,Leads!J:J,"perdido") | H7: =IFERROR(C7/B7,0) | I7: =IFERROR(D7/C7,0) | J7: =IFERROR(E7/D7,0) | K7: =IFERROR(F7/E7,0) | L7: =SUMIFS(Leads!T:T,Leads!H:H,A7,Leads!F:F,$B$4) | M7: =SUMIFS(Leads!V:V,Leads!H:H,A7,Leads!F:F,$B$4)
A8: Marta | B8: =COUNTIFS(Leads!H:H,A8,Leads!F:F,$B$4) | C8: =COUNTIFS(Leads!H:H,A8,Leads!F:F,$B$4,Leads!J:J,"<>frio") | D8: =COUNTIFS(Leads!H:H,A8,Leads!F:F,$B$4,Leads!J:J,"cita agendada")+COUNTIFS(Leads!H:H,A8,Leads!F:F,$B$4,Leads!J:J,"presentado")+COUNTIFS(Leads!H:H,A8,Leads!F:F,$B$4,Leads!J:J,"cerrado") | E8: =COUNTIFS(Leads!H:H,A8,Leads!F:F,$B$4,Leads!J:J,"presentado")+COUNTIFS(Leads!H:H,A8,Leads!F:F,$B$4,Leads!J:J,"cerrado") | F8: =COUNTIFS(Leads!H:H,A8,Leads!F:F,$B$4,Leads!J:J,"cerrado") | G8: =COUNTIFS(Leads!H:H,A8,Leads!F:F,$B$4,Leads!J:J,"perdido") | H8: =IFERROR(C8/B8,0) | I8: =IFERROR(D8/C8,0) | J8: =IFERROR(E8/D8,0) | K8: =IFERROR(F8/E8,0) | L8: =SUMIFS(Leads!T:T,Leads!H:H,A8,Leads!F:F,$B$4) | M8: =SUMIFS(Leads!V:V,Leads!H:H,A8,Leads!F:F,$B$4)
A9: José | B9: =COUNTIFS(Leads!H:H,A9,Leads!F:F,$B$4) | C9: =COUNTIFS(Leads!H:H,A9,Leads!F:F,$B$4,Leads!J:J,"<>frio") | D9: =COUNTIFS(Leads!H:H,A9,Leads!F:F,$B$4,Leads!J:J,"cita agendada")+COUNTIFS(Leads!H:H,A9,Leads!F:F,$B$4,Leads!J:J,"presentado")+COUNTIFS(Leads!H:H,A9,Leads!F:F,$B$4,Leads!J:J,"cerrado") | E9: =COUNTIFS(Leads!H:H,A9,Leads!F:F,$B$4,Leads!J:J,"presentado")+COUNTIFS(Leads!H:H,A9,Leads!F:F,$B$4,Leads!J:J,"cerrado") | F9: =COUNTIFS(Leads!H:H,A9,Leads!F:F,$B$4,Leads!J:J,"cerrado") | G9: =COUNTIFS(Leads!H:H,A9,Leads!F:F,$B$4,Leads!J:J,"perdido") | H9: =IFERROR(C9/B9,0) | I9: =IFERROR(D9/C9,0) | J9: =IFERROR(E9/D9,0) | K9: =IFERROR(F9/E9,0) | L9: =SUMIFS(Leads!T:T,Leads!H:H,A9,Leads!F:F,$B$4) | M9: =SUMIFS(Leads!V:V,Leads!H:H,A9,Leads!F:F,$B$4)

Sheet Comisiones
A1: Comisiones por persona (todos los lotes)
A2: Suma todas las comisiones generadas en Leads, por persona.
A4: Persona | B4: Rol | C4: € comisión setter | D4: € comisión closer | E4: € bonus mantenimiento | F4: € TOTAL
A5: Lucía | B5: setter | C5: =SUMIF(Leads!H:H,A5,Leads!V:V) | D5: =SUMIF(Leads!I:I,A5,Leads!W:W) | E5: =SUMIF(Leads!I:I,A5,Leads!X:X) | F5: =C5+D5+E5
A6: Marta | B6: setter | C6: =SUMIF(Leads!H:H,A6,Leads!V:V) | D6: =SUMIF(Leads!I:I,A6,Leads!W:W) | E6: =SUMIF(Leads!I:I,A6,Leads!X:X) | F6: =C6+D6+E6
A7: Diego | B7: closer | C7: =SUMIF(Leads!H:H,A7,Leads!V:V) | D7: =SUMIF(Leads!I:I,A7,Leads!W:W) | E7: =SUMIF(Leads!I:I,A7,Leads!X:X) | F7: =C7+D7+E7
A8: Sara | B8: closer | C8: =SUMIF(Leads!H:H,A8,Leads!V:V) | D8: =SUMIF(Leads!I:I,A8,Leads!W:W) | E8: =SUMIF(Leads!I:I,A8,Leads!X:X) | F8: =C8+D8+E8
A9: José | B9: closer | C9: =SUMIF(Leads!H:H,A9,Leads!V:V) | D9: =SUMIF(Leads!I:I,A9,Leads!W:W) | E9: =SUMIF(Leads!I:I,A9,Leads!X:X) | F9: =C9+D9+E9

Sheet Round-Robin
A1: Reparto round-robin de los 10.000 leads fríos
A3: Pega abajo (columna B) la lista de leads fríos. La columna 'Pareja' se rellena sola alternando Lucia-Diego / Marta-Sara / Jose. La columna 'Lote' agrupa en cohortes de 500.
A5: # | B5: Nombre psicólogo | C5: Pareja | D5: Lote
A6: 1 | C6: =IF(B6="","",CHOOSE(MOD(A6-1,3)+1,"Lucia-Diego","Marta-Sara","Jose")) | D6: =IF(B6="","",INT((A6-1)/500)+1)
A7: 2 | C7: =IF(B7="","",CHOOSE(MOD(A7-1,3)+1,"Lucia-Diego","Marta-Sara","Jose")) | D7: =IF(B7="","",INT((A7-1)/500)+1)
A8: 3 | C8: =IF(B8="","",CHOOSE(MOD(A8-1,3)+1,"Lucia-Diego","Marta-Sara","Jose")) | D8: =IF(B8="","",INT((A8-1)/500)+1)
A9: 4 | C9: =IF(B9="","",CHOOSE(MOD(A9-1,3)+1,"Lucia-Diego","Marta-Sara","Jose")) | D9: =IF(B9="","",INT((A9-1)/500)+1)
A10: 5 | C10: =IF(B10="","",CHOOSE(MOD(A10-1,3)+1,"Lucia-Diego","Marta-Sara","Jose")) | D10: =IF(B10="","",INT((A10-1)/500)+1)
A11: 6 | C11: =IF(B11="","",CHOOSE(MOD(A11-1,3)+1,"Lucia-Diego","Marta-Sara","Jose")) | D11: =IF(B11="","",INT((A11-1)/500)+1)
A12: 7 | C12: =IF(B12="","",CHOOSE(MOD(A12-1,3)+1,"Lucia-Diego","Marta-Sara","Jose")) | D12: =IF(B12="","",INT((A12-1)/500)+1)
A13: 8 | C13: =IF(B13="","",CHOOSE(MOD(A13-1,3)+1,"Lucia-Diego","Marta-Sara","Jose")) | D13: =IF(B13="","",INT((A13-1)/500)+1)
A14: 9 | C14: =IF(B14="","",CHOOSE(MOD(A14-1,3)+1,"Lucia-Diego","Marta-Sara","Jose")) | D14: =IF(B14="","",INT((A14-1)/500)+1)
A15: 10 | C15: =IF(B15="","",CHOOSE(MOD(A15-1,3)+1,"Lucia-Diego","Marta-Sara","Jose")) | D15: =IF(B15="","",INT((A15-1)/500)+1)
A16: 11 | C16: =IF(B16="","",CHOOSE(MOD(A16-1,3)+1,"Lucia-Diego","Marta-Sara","Jose")) | D16: =IF(B16="","",INT((A16-1)/500)+1)
A17: 12 | C17: =IF(B17="","",CHOOSE(MOD(A17-1,3)+1,"Lucia-Diego","Marta-Sara","Jose")) | D17: =IF(B17="","",INT((A17-1)/500)+1)
... A205: 200 | C205: =IF(B205="","",CHOOSE(MOD(A205-1,3)+1,"Lucia-Diego","Marta-Sara","Jose")) | D205: =IF(B205="","",INT((A205-1)/500)+1)
